workedon/__init__.py
workedon/__main__.py
workedon/_version.py
workedon/cli.py
workedon/conf.py
workedon/constants.py
workedon/default_settings.py
workedon/exceptions.py
workedon/models.py
workedon/parser.py
workedon/utils.py
workedon/workedon.py
workedon-0.8.0.dist-info/METADATA
workedon-0.8.0.dist-info/WHEEL
workedon-0.8.0.dist-info/entry_points.txt
workedon-0.8.0.dist-info/licenses/LICENSE
workedon-0.8.0.dist-info/RECORD
