Metadata-Version: 2.4
Name: workedon
Version: 0.8.0
Summary: Work tracking from your shell.
Project-URL: Homepage, https://github.com/viseshrp/workedon
Project-URL: Repository, https://github.com/viseshrp/workedon
Project-URL: Documentation, https://github.com/viseshrp/workedon/blob/main/README.md
Project-URL: Changelog, https://github.com/viseshrp/workedon/blob/main/CHANGELOG.md
Project-URL: Bug-Tracker, https://github.com/viseshrp/workedon/issues
Project-URL: CI, https://github.com/viseshrp/workedon/actions
Author-email: Visesh Prasad <viseshrprasad@gmail.com>
License: MIT
License-File: LICENSE
Keywords: journal,log,work,workedon,worklog
Classifier: Development Status :: 4 - Beta
Classifier: Environment :: Console
Classifier: Intended Audience :: Developers
Classifier: License :: OSI Approved :: MIT License
Classifier: Natural Language :: English
Classifier: Operating System :: OS Independent
Classifier: Programming Language :: Python
Classifier: Programming Language :: Python :: 3
Classifier: Programming Language :: Python :: 3.9
Classifier: Programming Language :: Python :: 3.10
Classifier: Programming Language :: Python :: 3.11
Classifier: Programming Language :: Python :: 3.12
Classifier: Programming Language :: Python :: 3.13
Classifier: Topic :: Software Development :: Libraries :: Python Modules
Requires-Python: <4.0,>=3.9
Requires-Dist: click-default-group<2.0.0,>=1.2.4
Requires-Dist: click<8.2.0,>=8.1.1
Requires-Dist: dateparser<1.2.1,>=1.1.4
Requires-Dist: peewee<4.0.0,>=3.18.1
Requires-Dist: platformdirs<5.0.0,>=4.3.8
Requires-Dist: tzlocal<5.3.2,>=4.0.0
